pandomics/__init__.py
pandomics/__version__
pandomics/utils.py
pandomics/visualization_tools.py
pandomics-0.0.9.dist-info/DESCRIPTION.rst
pandomics-0.0.9.dist-info/METADATA
pandomics-0.0.9.dist-info/RECORD
pandomics-0.0.9.dist-info/WHEEL
pandomics-0.0.9.dist-info/metadata.json
pandomics-0.0.9.dist-info/top_level.txt
