Metadata-Version: 2.0
Name: pandomics
Version: 0.0.9
Summary: Omics flavored pandas
Home-page: https://github.com/draperjames/panomics
Author: James Draper
Author-email: james.draper@duke.edu
License: MIT
Keywords: pandas
Platform: UNKNOWN
Classifier: Development Status :: 3 - Alpha
Classifier: Intended Audience :: Developers
Classifier: Topic :: Software Development :: Build Tools
Classifier: License :: OSI Approved :: MIT License
Classifier: Programming Language :: Python :: 3.4
Classifier: Programming Language :: Python :: 3.5
Requires-Dist: pandas
Requires-Dist: xlrd
Requires-Dist: numpy
